arkfbp/__init__.py
arkfbp/executer.py
arkfbp/flow.py
arkfbp/graph.py
arkfbp/request.py
arkfbp/response.py
arkfbp/stack.py
arkfbp/bin/arkfbp.py
arkfbp/common/__init__.py
arkfbp/common/api_visualization.py
arkfbp/common/django/__init__.py
arkfbp/common/django/app/__init__.py
arkfbp/common/django/app/automation/__init__.py
arkfbp/common/django/app/automation/apps.py
arkfbp/common/django/app/automation/api_config/pagination.json
arkfbp/common/django/app/automation/flows/__init__.py
arkfbp/common/django/app/automation/flows/core.py
arkfbp/common/django/app/automation/flows/modeling.py
arkfbp/common/django/app/automation/flows/admin/__init__.py
arkfbp/common/django/app/automation/flows/admin/main.py
arkfbp/common/django/app/automation/flows/admin/nodes/__init__.py
arkfbp/common/django/app/automation/flows/admin/nodes/permission.py
arkfbp/common/django/app/automation/flows/admin/nodes/serializer.py
arkfbp/common/django/app/automation/flows/meta_config/__init__.py
arkfbp/common/django/app/automation/flows/meta_config/main.py
arkfbp/common/django/app/automation/flows/meta_config/nodes/__init__.py
arkfbp/common/django/app/automation/flows/meta_config/nodes/config.py
arkfbp/common/django/app/automation/migrations/__init__.py
arkfbp/common/django/conf/__init__.py
arkfbp/common/django/conf/app_template/__init__.py-tpl
arkfbp/common/django/conf/app_template/admin.py-tpl
arkfbp/common/django/conf/app_template/apps.py-tpl
arkfbp/common/django/conf/app_template/models.py-tpl
arkfbp/common/django/conf/app_template/tests.py-tpl
arkfbp/common/django/conf/app_template/views.py-tpl
arkfbp/common/django/conf/app_template/flows/__init__.py-tpl
arkfbp/common/django/conf/app_template/migrations/__init__.py-tpl
arkfbp/common/django/conf/flow_template/__init__.py-tpl
arkfbp/common/django/conf/flow_template/main.py-tpl
arkfbp/common/django/conf/flow_template/nodes/__init__.py-tpl
arkfbp/common/django/conf/node_template/app_name.py-tpl
arkfbp/common/django/conf/project_template/manage.py-tpl
arkfbp-0.0.3.dist-info/LICENSE
arkfbp-0.0.3.dist-info/METADATA
arkfbp-0.0.3.dist-info/WHEEL
arkfbp-0.0.3.dist-info/entry_points.txt
arkfbp-0.0.3.dist-info/top_level.txt
arkfbp-0.0.3.dist-info/RECORD
